snaketerm/__init__.py
snaketerm/game.py
snaketerm/main.py
snaketerm/snake.py
snake_terminal-1.0.0.dist-info/METADATA
snake_terminal-1.0.0.dist-info/WHEEL
snake_terminal-1.0.0.dist-info/entry_points.txt
snake_terminal-1.0.0.dist-info/top_level.txt
snake_terminal-1.0.0.dist-info/RECORD
