Metadata-Version: 2.1
Name: snake-terminal
Version: 1.0.0
Summary: Snake game in your terminal
Home-page: https://github.com/busayojee/snake-terminal
Author: Alabi Busayo
Author-email: busayoalabi1234@gmail.com
License: UNKNOWN
Platform: UNKNOWN
Classifier: Environment :: Console :: Curses
Classifier: Natural Language :: English
Classifier: Operating System :: MacOS :: MacOS X
Classifier: Operating System :: POSIX
Classifier: Operating System :: Unix
Classifier: Programming Language :: Python :: 3
Classifier: Topic :: Utilities
Requires-Dist: curses-menu>=0.7.1
Requires-Dist: click>=8.1.7
